pyltr/__init__.py
pyltr/data/__init__.py
pyltr/data/letor.py
pyltr/data/pairwise_transform.py
pyltr/data/pandas_converter.py
pyltr/metrics/__init__.py
pyltr/metrics/_metrics.py
pyltr/metrics/ap.py
pyltr/metrics/dcg.py
pyltr/metrics/err.py
pyltr/metrics/gains.py
pyltr/metrics/kendall.py
pyltr/metrics/roc.py
pyltr/metrics/tests/__init__.py
pyltr/metrics/tests/helpers.py
pyltr/metrics/tests/test_ap.py
pyltr/metrics/tests/test_dcg.py
pyltr/metrics/tests/test_err.py
pyltr/metrics/tests/test_kendall.py
pyltr/metrics/tests/test_roc.py
pyltr/models/__init__.py
pyltr/models/_models.py
pyltr/models/lambdamart.py
pyltr/models/monitors.py
pyltr/util/__init__.py
pyltr/util/group.py
pyltr/util/sort.py
pyltr-0.2.6.dist-info/AUTHORS.txt
pyltr-0.2.6.dist-info/LICENSE.txt
pyltr-0.2.6.dist-info/METADATA
pyltr-0.2.6.dist-info/WHEEL
pyltr-0.2.6.dist-info/top_level.txt
pyltr-0.2.6.dist-info/zip-safe
pyltr-0.2.6.dist-info/RECORD
