Metadata-Version: 2.1
Name: pyltr
Version: 0.2.6
Summary: Python learning to rank (LTR) toolkit.
Home-page: https://github.com/jma127/pyltr
Author: Jerry Ma
Author-email: jmnospam@mail.com
License: BSD-new
Platform: UNKNOWN
Requires-Dist: numpy
Requires-Dist: pandas
Requires-Dist: scipy
Requires-Dist: scikit-learn
Requires-Dist: six
